pyup/__init__.py
pyup/cli.py
pyup/pyup.py
pyup-0.1.3.dist-info/entry_points.txt
pyup-0.1.3.dist-info/LICENSE
pyup-0.1.3.dist-info/WHEEL
pyup-0.1.3.dist-info/METADATA
pyup-0.1.3.dist-info/RECORD
