Metadata-Version: 2.1
Name: pyup
Version: 0.1.3
Summary: Caddy file server in Python with many additional features!
License: MIT
Author: Alyetama
Author-email: malyetama@pm.me
Requires-Python: >=3.6,<4.0
Classifier: License :: OSI Approved :: MIT License
Classifier: Programming Language :: Python :: 3
Classifier: Programming Language :: Python :: 3.10
Classifier: Programming Language :: Python :: 3.6
Classifier: Programming Language :: Python :: 3.7
Classifier: Programming Language :: Python :: 3.8
Classifier: Programming Language :: Python :: 3.9
Requires-Dist: loguru (>=0.5.3)
Requires-Dist: paramiko (>=2.10.2)
Requires-Dist: pymongo[srv] (>=4.0.2)
Requires-Dist: pyperclip (>=1.8.2)
Requires-Dist: python-dotenv (>=0.20.0)
Requires-Dist: rich (>=10.11.0)
Requires-Dist: tqdm (>=4.62.3)
